githerer/__init__.py
githerer/api.py
githerer/main.py
githerer-0.0.2.dist-info/licenses/LICENSE
githerer-0.0.2.dist-info/METADATA
githerer-0.0.2.dist-info/WHEEL
githerer-0.0.2.dist-info/entry_points.txt
githerer-0.0.2.dist-info/top_level.txt
githerer-0.0.2.dist-info/RECORD
