Metadata-Version: 2.4
Name: githerer
Version: 0.0.2
Summary: A tool used to clone organization repos using pattern-based matching
Author-email: Douglas Luman <dluman@allegheny.edu>
License-File: LICENSE
Requires-Dist: rich
Requires-Dist: arglite
Requires-Dist: GitPython
Requires-Dist: requests
Requires-Dist: python-dotenv
Dynamic: license-file
